LICENSE.txt
MANIFEST.in
README.rst
setup.py
cypunct/__init__.py
cypunct/cypunct.pyx
cypunct/test_suite.py
cypunct/unicode_classes.py
cypunct.egg-info/PKG-INFO
cypunct.egg-info/SOURCES.txt
cypunct.egg-info/dependency_links.txt
cypunct.egg-info/not-zip-safe
cypunct.egg-info/top_level.txt