Metadata-Version: 1.1
Name: cypunct
Version: 0.1.1
Summary: Cypunct is a Cython package to split Unicode strings based on a given frozenset of Unicode code points.
Home-page: https://github.com/jamesmishra/cypunct
Author: James Mishra
Author-email: j@jamesmishra.com
License: MIT
Keywords: unicode string splitting
Platform: UNKNOWN
Classifier: Environment :: Console
Classifier: Intended Audience :: Developers
Classifier: Operating System :: POSIX :: Linux
Classifier: Operating System :: MacOS :: MacOS X
Classifier: Operating System :: Microsoft :: Windows
Classifier: Programming Language :: Cython
Classifier: Programming Language :: Python :: 2.6
Classifier: Programming Language :: Python :: 2.7
Classifier: Programming Language :: Python :: 3.3
Classifier: Programming Language :: Python :: 3.4
Classifier: Programming Language :: Python :: 3.5
Classifier: Programming Language :: Python :: 3.6
